podder/__init__.py
podder/client.py
podder/exceptions.py
podder/helpers/__init__.py
podder/helpers/exception_helper.py
podder/job.py
podder/services/__init__.py
podder/services/api_service.py
podder-0.1.0.dist-info/WHEEL
podder-0.1.0.dist-info/METADATA
podder-0.1.0.dist-info/RECORD
